aucampia/__init__.py
aucampia/template/__init__.py
aucampia/template/poetry/__init__.py
aucampia/template/poetry/_version.py
aucampia/template/poetry/cli.py
aucampia/template/poetry/cli_click.py
aucampia/template/poetry/cli_typer.py
aucampia/template/poetry/py.typed
aucampia.template.poetry-0.1.4.dist-info/entry_points.txt
aucampia.template.poetry-0.1.4.dist-info/LICENSE
aucampia.template.poetry-0.1.4.dist-info/WHEEL
aucampia.template.poetry-0.1.4.dist-info/METADATA
aucampia.template.poetry-0.1.4.dist-info/RECORD
